LICENSE
LICENSE.txt
README.rst
setup.cfg
setup.py
ingsirapob/__init__.py
ingsirapob/ing.py
ingsirapob.egg-info/PKG-INFO
ingsirapob.egg-info/SOURCES.txt
ingsirapob.egg-info/dependency_links.txt
ingsirapob.egg-info/top_level.txt