Metadata-Version: 2.1
Name: ingsirapob
Version: 0.0.1
Summary: Who is sirapob???
Home-page: https://github.com/fluffyhugger
Author: Sirapob
Author-email: ingthefiaw@gmail.com
License: MIT
Download-URL: https://github.com/fluffyhugger
Keywords: Ingsirapob,ASCII ART
Platform: UNKNOWN
Classifier: Development Status :: 3 - Alpha
Classifier: Intended Audience :: Education
Classifier: Topic :: Utilities
Classifier: License :: OSI Approved :: MIT License
Classifier: Programming Language :: Python :: 3
Classifier: Programming Language :: Python :: 3.4
Classifier: Programming Language :: Python :: 3.5
Classifier: Programming Language :: Python :: 3.6
Classifier: Programming Language :: Python :: 3.7
Classifier: Programming Language :: Python :: 3.8
Classifier: Programming Language :: Python :: 3.9
Classifier: Programming Language :: Python :: 3.10
License-File: LICENSE
License-File: LICENSE.txt
